ks_binance_spot_market_api/./.gitignore
ks_binance_spot_market_api/./LICENSE.txt
ks_binance_spot_market_api/./README.en.md
ks_binance_spot_market_api/./README.md
ks_binance_spot_market_api/./__about__.py
ks_binance_spot_market_api/./__init__.py
ks_binance_spot_market_api/./ks_binance_spot_market_api.py
ks_binance_spot_market_api/./pyproject.toml
ks_binance_spot_market_api/./requirements.txt
ks_binance_spot_market_api/./setup.py
ks_binance_spot_market_api-0.0.9.dist-info/METADATA
ks_binance_spot_market_api-0.0.9.dist-info/WHEEL
ks_binance_spot_market_api-0.0.9.dist-info/licenses/LICENSE.txt
ks_binance_spot_market_api-0.0.9.dist-info/RECORD
